README.md
setup.py
OptiPrompt.egg-info/PKG-INFO
OptiPrompt.egg-info/SOURCES.txt
OptiPrompt.egg-info/dependency_links.txt
OptiPrompt.egg-info/entry_points.txt
OptiPrompt.egg-info/requires.txt
OptiPrompt.egg-info/top_level.txt
optiprompt/__init__.py
optiprompt/constants.py
optiprompt/main.py
optiprompt/approximate_cost/__init__.py
optiprompt/approximate_cost/cost.py
optiprompt/cost/__init__.py
optiprompt/cost/embeddings.py
optiprompt/cost/input.py
optiprompt/cost/output.py
optiprompt/doc/doc.md
optiprompt/evals/__init__.py
optiprompt/evals/classification.py
optiprompt/evals/code_generation.py
optiprompt/evals/elovalue.py
optiprompt/evals/equals.py
optiprompt/evals/function_calling.py
optiprompt/evals/includes.py
optiprompt/evals/json_validation.py
optiprompt/evals/semantic_similarity.py
optiprompt/openai_calls/__init__.py
optiprompt/openai_calls/openai_call.py
optiprompt/prompt_generation/__init__.py
optiprompt/prompt_generation/generation.py
optiprompt/prompt_generation/iteration.py
optiprompt/validation_yaml/__init__.py
optiprompt/validation_yaml/validation.py