Metadata-Version: 2.1
Name: OptiPrompt
Version: 0.0.3
Summary: Prompt Engineer (OptiPrompt) is a package for evaluating custom prompts using various evaluation methods. It allows you to provide your own prompts or generate them automatically and then obtain the results in a JSON file.
Requires-Python: >=3.8
